examples/__init__.py
examples/tests.py
geoh/__init__.py
geoh/geoh.py
geoh-0.1.dist-info/DESCRIPTION.rst
geoh-0.1.dist-info/METADATA
geoh-0.1.dist-info/RECORD
geoh-0.1.dist-info/WHEEL
geoh-0.1.dist-info/metadata.json
geoh-0.1.dist-info/top_level.txt
