Metadata-Version: 2.0
Name: geoh
Version: 0.1
Summary: Transform a geoJSON into a list of geohashes that intersect with it
Home-page: https://github.com/mathieuripert/geoh
Author: Mathieu Ripert
Author-email: mathieu@instacart.com
License: MIT
Platform: UNKNOWN
Requires-Dist: geopandas (>=0.2)
Requires-Dist: pandas (>=0.15.2)
Requires-Dist: python-geohash (>=0.8.5)
Requires-Dist: shapely (>=1.5.13)
